{
  "swagger": "2.0",
  "info": {
    "title": "form_example.proto",
    "version": "version not set"
  },
  "consumes": [
    "application/json"
  ],
  "produces": [
    "application/json"
  ],
  "paths": {
    "/v2/bar": {
      "post": {
        "operationId": "Post",
        "responses": {
          "200": {
            "description": "A successful response.",
            "schema": {
              "$ref": "#/definitions/foo.bar.sdk.FooResponse"
            }
          },
          "default": {
            "description": "An unexpected error response",
            "schema": {
              "$ref": "#/definitions/grpc.gateway.runtime.Error"
            }
          }
        },
        "parameters": [
          {
            "name": "body",
            "in": "body",
            "required": true,
            "schema": {
              "$ref": "#/definitions/foo.bar.sdk.FooRequest"
            }
          }
        ],
        "tags": [
          "FooAPI"
        ]
      }
    }
  },
  "definitions": {
    "foo.bar.sdk.FooRequest": {
      "type": "object",
      "properties": {
        "name": {
          "type": "string",
          "title": "@inject_tag: validate:\"required,gt=0\" form:\"name\""
        }
      }
    },
    "foo.bar.sdk.FooResponse": {
      "type": "object",
      "properties": {
        "body": {
          "type": "string",
          "title": "Actual items"
        }
      }
    },
    "google.protobuf.Any": {
      "type": "object",
      "properties": {
        "type_url": {
          "type": "string"
        },
        "value": {
          "type": "string",
          "format": "byte"
        }
      }
    },
    "grpc.gateway.runtime.Error": {
      "type": "object",
      "properties": {
        "error": {
          "type": "string"
        },
        "code": {
          "type": "integer",
          "format": "int32"
        },
        "message": {
          "type": "string"
        },
        "details": {
          "type": "array",
          "items": {
            "$ref": "#/definitions/google.protobuf.Any"
          }
        }
      }
    }
  }
}
